{
	"info": {
		"_postman_id": "7da9f2e6-42c9-43e8-b0a5-67436ea25a4d",
		"name": "api-post",
		"schema": "https://schema.getpostman.com/json/collection/v2.1.0/collection.json",
		"_exporter_id": "34172375"
	},
	"item": [
		{
			"name": "(create) api-post",
			"request": {
				"method": "POST",
				"header": [],
				"body": {
					"mode": "raw",
					"raw": "{\r\n    \"title\": \"El post nuevo\",\r\n    \"text\": \"Este es el nuevo texto\",\r\n    \"author\": \"MaRcos\"\r\n}",
					"options": {
						"raw": {
							"language": "json"
						}
					}
				},
				"url": {
					"raw": "http://localhost:3000/api/posts",
					"protocol": "http",
					"host": [
						"localhost"
					],
					"port": "3000",
					"path": [
						"api",
						"posts"
					]
				}
			},
			"response": []
		},
		{
			"name": "(list) api-post",
			"protocolProfileBehavior": {
				"disableBodyPruning": true
			},
			"request": {
				"method": "GET",
				"header": [],
				"body": {
					"mode": "raw",
					"raw": "{\r\n    \"title\": \"El post nuevo\",\r\n    \"text\": \"Este es el nuevo texto\",\r\n    \"author\": \"MaRcos\"\r\n}",
					"options": {
						"raw": {
							"language": "json"
						}
					}
				},
				"url": {
					"raw": "http://localhost:3000/api/posts",
					"protocol": "http",
					"host": [
						"localhost"
					],
					"port": "3000",
					"path": [
						"api",
						"posts"
					]
				}
			},
			"response": []
		},
		{
			"name": "(detail) api-post",
			"protocolProfileBehavior": {
				"disableBodyPruning": true
			},
			"request": {
				"method": "GET",
				"header": [],
				"body": {
					"mode": "raw",
					"raw": "{\r\n    \"title\": \"El post nuevo\",\r\n    \"text\": \"Este es el nuevo texto\",\r\n    \"author\": \"MaRcos\"\r\n}",
					"options": {
						"raw": {
							"language": "json"
						}
					}
				},
				"url": {
					"raw": "http://localhost:3000/api/posts/661930528205c771887bb473",
					"protocol": "http",
					"host": [
						"localhost"
					],
					"port": "3000",
					"path": [
						"api",
						"posts",
						"661930528205c771887bb473"
					]
				}
			},
			"response": []
		},
		{
			"name": "(update) api-post",
			"protocolProfileBehavior": {
				"disableBodyPruning": true
			},
			"request": {
				"method": "GET",
				"header": [],
				"body": {
					"mode": "raw",
					"raw": "{\r\n    \"title\": \"El post nuevo\",\r\n    \"text\": \"Este es el nuevo texto\",\r\n    \"author\": \"MaRcos\"\r\n}",
					"options": {
						"raw": {
							"language": "json"
						}
					}
				},
				"url": {
					"raw": "http://localhost:3000/api/posts/661930528205c771887bb473",
					"protocol": "http",
					"host": [
						"localhost"
					],
					"port": "3000",
					"path": [
						"api",
						"posts",
						"661930528205c771887bb473"
					]
				}
			},
			"response": []
		},
		{
			"name": "(delete)api-post",
			"request": {
				"method": "DELETE",
				"header": [],
				"url": {
					"raw": "http://localhost:3000/api/posts/6619254cf70defc07ca64ed4",
					"protocol": "http",
					"host": [
						"localhost"
					],
					"port": "3000",
					"path": [
						"api",
						"posts",
						"6619254cf70defc07ca64ed4"
					]
				}
			},
			"response": []
		}
	]
}